[
    {
        "id": "50825659378",
        "owner": "49048066@N06",
        "secret": "ee1d478851",
        "server": "65535",
        "farm": 66,
        "title": "Pollock Mountain",
        "ispublic": 1,
        "license": 4,
        "flickr_url": "https://farm66.staticflickr.com/65535/50825659378_ee1d478851_z.jpg",
        "file_name": "50825659378.jpg",
        "date_captured": "04/27/2021, 19:10:25",
        "width": 640,
        "height": 400
    },
    {
        "id": "50826398846",
        "owner": "49048066@N06",
        "secret": "54e729a5bc",
        "server": "65535",
        "farm": 66,
        "title": "Ice Crossing",
        "ispublic": 1,
        "license": 4,
        "flickr_url": "https://farm66.staticflickr.com/65535/50826398846_54e729a5bc_z.jpg",
        "file_name": "50826398846.jpg",
        "date_captured": "04/27/2021, 19:10:27",
        "width": 640,
        "height": 427
    },
    {
        "id": "50826402791",
        "owner": "49048066@N06",
        "secret": "385116afd4",
        "server": "65535",
        "farm": 66,
        "title": "Piegan Mountain",
        "ispublic": 1,
        "license": 4,
        "flickr_url": "https://farm66.staticflickr.com/65535/50826402791_385116afd4_z.jpg",
        "file_name": "50826402791.jpg",
        "date_captured": "04/27/2021, 19:10:26",
        "width": 640,
        "height": 360
    }
]