<?xml version='1.0' encoding='utf-8'?>
<annotations>
  <version>1.1</version>
  <meta>
    <task>
      <id>327</id>
      <name>j_lighthouse_part 3</name>
      <size>11</size>
      <mode>annotation</mode>
      <overlap>0</overlap>
      <bugtracker />
      <created>2021-07-30 14:22:26.814918+00:00</created>
      <updated>2021-07-30 14:22:26.814936+00:00</updated>
      <start_frame>0</start_frame>
      <stop_frame>10</stop_frame>
      <frame_filter />
      <z_order>True</z_order>
      <labels>
        <label>
          <name>building</name>
          <color>#204000</color>
          <attributes>
          </attributes>
        </label>
        <label>
          <name>hot_spring</name>
          <color>#1771c8</color>
          <attributes>
          </attributes>
        </label>
        <label>
          <name>pole</name>
          <color>#60a0a0</color>
          <attributes>
          </attributes>
        </label>
        <label>
          <name>traffic_sign</name>
          <color>#502080</color>
          <attributes>
          </attributes>
        </label>
        <label>
          <name>wetland</name>
          <color>#545b93</color>
          <attributes>
          </attributes>
        </label>
        <label>
          <name>waterfall</name>
          <color>#2718ba</color>
          <attributes>
          </attributes>
        </label>
        <label>
          <name>water_well</name>
          <color>#fe1771</color>
          <attributes>
          </attributes>
        </label>
        <label>
          <name>water_tower</name>
          <color>#d68d03</color>
          <attributes>
          </attributes>
        </label>
        <label>
          <name>wall</name>
          <color>#d020c0</color>
          <attributes>
          </attributes>
        </label>
        <label>
          <name>vegetation</name>
          <color>#9020c0</color>
          <attributes>
          </attributes>
        </label>
        <label>
          <name>umbrella</name>
          <color>#d06080</color>
          <attributes>
          </attributes>
        </label>
        <label>
          <name>truck</name>
          <color>#906080</color>
          <attributes>
          </attributes>
        </label>
        <label>
          <name>train</name>
          <color>#50a080</color>
          <attributes>
          </attributes>
        </label>
        <label>
          <name>terrain</name>
          <color>#f04040</color>
          <attributes>
          </attributes>
        </label>
        <label>
          <name>swimming_pool</name>
          <color>#b00040</color>
          <attributes>
          </attributes>
        </label>
        <label>
          <name>spillway</name>
          <color>#188bb1</color>
          <attributes>
          </attributes>
        </label>
        <label>
          <name>snow</name>
          <color>#104040</color>
          <attributes>
          </attributes>
        </label>
        <label>
          <name>sky</name>
          <color>#508040</color>
          <attributes>
          </attributes>
        </label>
        <label>
          <name>sidewalk</name>
          <color>#108040</color>
          <attributes>
          </attributes>
        </label>
        <label>
          <name>shoreline</name>
          <color>#fe3659</color>
          <attributes>
          </attributes>
        </label>
        <label>
          <name>ship</name>
          <color>#769ef8</color>
          <attributes>
          </attributes>
        </label>
        <label>
          <name>sea</name>
          <color>#508080</color>
          <attributes>
          </attributes>
        </label>
        <label>
          <name>road</name>
          <color>#20e0e0</color>
          <attributes>
          </attributes>
        </label>
        <label>
          <name>river_delta</name>
          <color>#8ac8bb</color>
          <attributes>
          </attributes>
        </label>
        <label>
          <name>river</name>
          <color>#a060e0</color>
          <attributes>
          </attributes>
        </label>
        <label>
          <name>reservoir</name>
          <color>#3a53cf</color>
          <attributes>
          </attributes>
        </label>
        <label>
          <name>rapids</name>
          <color>#be9a1a</color>
          <attributes>
          </attributes>
        </label>
        <label>
          <name>puddle</name>
          <color>#5cf456</color>
          <attributes>
          </attributes>
        </label>
        <label>
          <name>pipeline</name>
          <color>#a95686</color>
          <attributes>
          </attributes>
        </label>
        <label>
          <name>pier</name>
          <color>#dd5810</color>
          <attributes>
          </attributes>
        </label>
        <label>
          <name>person</name>
          <color>#c06060</color>
          <attributes>
          </attributes>
        </label>
        <label>
          <name>parking_meter</name>
          <color>#c020e0</color>
          <attributes>
          </attributes>
        </label>
        <label>
          <name>offshore_platform</name>
          <color>#76a436</color>
          <attributes>
          </attributes>
        </label>
        <label>
          <name>motorcycle</name>
          <color>#80a0a0</color>
          <attributes>
          </attributes>
        </label>
        <label>
          <name>marsh</name>
          <color>#1cc0bd</color>
          <attributes>
          </attributes>
        </label>
        <label>
          <name>mangrove</name>
          <color>#fee8f4</color>
          <attributes>
          </attributes>
        </label>
        <label>
          <name>lighthouse</name>
          <color>#a08060</color>
          <attributes>
          </attributes>
        </label>
        <label>
          <name>levee</name>
          <color>#2aaeab</color>
          <attributes>
          </attributes>
        </label>
        <label>
          <name>lake</name>
          <color>#2037eb</color>
          <attributes>
          </attributes>
        </label>
        <label>
          <name>glaciers</name>
          <color>#3856f8</color>
          <attributes>
          </attributes>
        </label>
        <label>
          <name>flood</name>
          <color>#520896</color>
          <attributes>
          </attributes>
        </label>
        <label>
          <name>fjord</name>
          <color>#49da6e</color>
          <attributes>
          </attributes>
        </label>
        <label>
          <name>fire_hydrant</name>
          <color>#e0e000</color>
          <attributes>
          </attributes>
        </label>
        <label>
          <name>fence</name>
          <color>#20e080</color>
          <attributes>
          </attributes>
        </label>
        <label>
          <name>ditch</name>
          <color>#7fc485</color>
          <attributes>
          </attributes>
        </label>
        <label>
          <name>dam</name>
          <color>#7dd16d</color>
          <attributes>
          </attributes>
        </label>
        <label>
          <name>cypress_tree</name>
          <color>#0c335b</color>
          <attributes>
          </attributes>
        </label>
        <label>
          <name>culvert</name>
          <color>#143890</color>
          <attributes>
          </attributes>
        </label>
        <label>
          <name>cliff</name>
          <color>#047db5</color>
          <attributes>
          </attributes>
        </label>
        <label>
          <name>car</name>
          <color>#2080c0</color>
          <attributes>
          </attributes>
        </label>
        <label>
          <name>canal</name>
          <color>#308d2e</color>
          <attributes>
          </attributes>
        </label>
        <label>
          <name>bus</name>
          <color>#204080</color>
          <attributes>
          </attributes>
        </label>
        <label>
          <name>bridge</name>
          <color>#e08000</color>
          <attributes>
          </attributes>
        </label>
        <label>
          <name>breakwater</name>
          <color>#172ece</color>
          <attributes>
          </attributes>
        </label>
        <label>
          <name>boat</name>
          <color>#4040c0</color>
          <attributes>
          </attributes>
        </label>
        <label>
          <name>bicycle</name>
          <color>#004040</color>
          <attributes>
          </attributes>
        </label>
      </labels>
      <segments>
        <segment>
          <id>319</id>
          <start>0</start>
          <stop>10</stop>
          <url>http://localhost:8080/?id=319</url>
        </segment>
      </segments>
      <owner>
        <username>cvat</username>
        <email />
      </owner>
      <assignee />
    </task>
    <dumped>2021-07-30 14:53:21.379759+00:00</dumped>
  </meta>
  <image height="640" id="10" name="51116991192.jpg" width="640">
  <polygon label="sky" occluded="0" points="35.46,34.67;605.65,35.46;604.47,440.65;35.46,457.66" source="manual" z_order="-1">
    </polygon>
    <polygon label="sea" occluded="0" points="35.06,383.59;605.34,385.01;603.90,604.60;35.54,604.86" source="manual" z_order="0">
    </polygon>
    <polygon label="levee" occluded="0" points="148.23,604.93;155.16,596.35;154.50,590.42;159.11,584.48;160.43,581.52;161.42,578.55;161.75,577.89;169.66,565.36;177.25,556.79;183.18,555.14;182.52,546.89;190.11,540.96;193.74,533.04;198.02,525.79;201.32,525.13;206.60,516.23;206.60,512.93;212.86,505.02;217.48,500.07;226.05,487.54;236.60,472.04;245.84,461.82;246.49,458.85;250.45,454.23;255.40,445.99;258.37,442.36;265.62,431.48;275.18,416.64;268.26,413.02;267.93,412.69;256.72,408.40;256.39,407.08;251.11,407.08;252.10,405.10;256.72,401.80;257.05,394.22;258.37,394.22;259.03,387.96;272.21,387.30;301.23,387.96;301.56,390.92;303.21,391.58;304.53,395.87;329.26,399.83;344.43,401.80;353.66,405.76;371.80,414.34;381.03,418.29;381.36,415.65;388.94,415.98;388.62,421.59;415.32,432.47;420.27,434.78;424.23,434.45;425.22,436.76;425.55,436.76;436.43,440.06;446.65,445.00;457.86,449.29;474.02,456.21;482.92,460.17;486.88,461.16;493.80,463.14;503.70,467.42;504.03,469.07;524.80,476.00;538.98,483.25;553.16,490.51;562.06,492.81;568.00,492.16;569.32,497.10;578.55,499.41;587.12,499.74;588.44,504.03;604.27,509.30;604.93,605.26" source="manual" z_order="1">
    </polygon>
    <polygon label="lighthouse" occluded="0" points="272.58,388.82;274.48,353.99;273.85,353.68;273.69,352.09;275.91,351.13;279.73,346.20;279.73,344.13;280.84,344.13;281.00,345.88;284.50,349.86;287.20,352.40;287.36,353.68;285.77,353.83;288.16,377.21;288.16,388.98;289.59,389.61;289.75,391.52;273.53,389.61" source="manual" z_order="2">
    </polygon>
    <polygon label="sidewalk" occluded="0" points="382.90,605.10;323.68,443.92;317.20,428.66;321.83,428.20;321.37,418.49;315.35,418.02;313.97,414.79;313.04,414.32;310.27,408.77;312.58,407.39;313.04,405.07;314.89,403.69;314.43,401.37;314.43,399.52;323.22,400.91;325.53,401.37;327.84,402.76;329.69,404.15;332.00,405.54;333.85,407.39;335.24,409.24;336.63,411.09;337.55,412.01;339.86,412.01;378.25,441.15;417.10,468.43;495.26,529.02;603.20,605.20" source="manual" z_order="2">
    </polygon>
  </image>
  <image height="426" id="9" name="51103241872.jpg" width="640">
  <polygon label="sky" occluded="0" points="0.00,0.00;640.00,0.00;640.00,345.84;0.00,332.60" source="manual" z_order="-2">
    </polygon>
    <polygon label="lighthouse" occluded="0" points="226.97,262.16;233.10,215.10;235.56,163.12;234.74,149.21;233.10,146.75;231.06,145.12;229.42,144.71;228.19,141.43;230.65,138.98;231.88,127.11;237.61,127.52;242.52,126.70;243.34,103.78;240.88,102.96;242.52,99.28;248.66,87.82;253.16,86.59;255.61,73.91;257.66,70.63;260.11,71.04;259.71,68.18;256.43,66.54;256.84,63.27;260.11,63.68;260.52,58.35;262.16,59.17;262.57,62.45;265.43,63.68;269.12,63.68;267.89,68.18;265.03,68.59;263.80,71.45;267.07,73.91;269.94,78.41;269.94,84.55;277.30,91.50;281.40,100.51;281.40,103.37;279.76,103.78;280.17,114.42;279.35,120.15;279.35,125.47;283.03,126.70;285.49,126.70;285.49,121.38;288.76,118.51;292.45,118.51;294.08,123.02;292.85,127.52;294.08,136.52;290.40,136.52;290.40,138.98;294.49,141.84;292.85,145.52;289.17,145.52;287.13,151.66;287.53,177.04;289.58,224.92;296.95,266.66;297.36,269.53;306.36,270.76;305.54,280.17;306.77,303.09;247.84,300.22" source="manual" z_order="-1">
    </polygon>
    <polygon label="sea" occluded="0" points="0.00,317.90;11.81,305.39;11.81,301.13;18.92,296.58;22.05,291.75;48.19,276.69;69.51,270.15;73.20,267.31;70.93,263.62;73.20,259.92;78.32,254.24;80.59,251.40;113.27,239.46;139.42,231.22;149.65,234.06;155.34,234.34;167.84,232.92;173.24,232.07;177.79,231.50;182.62,230.08;188.59,229.80;194.84,230.36;199.67,230.65;204.79,234.34;208.77,236.62;212.46,240.31;213.03,244.86;220.42,248.84;226.10,251.40;231.22,252.82;238.32,254.24;243.15,257.36;253.10,256.80;257.93,257.08;263.33,260.21;264.18,266.17;264.75,270.72;266.46,275.55;267.03,280.10;276.69,287.49;282.94,292.04;292.89,296.01;298.57,297.44;304.54,297.15;309.94,295.45;315.06,294.03;321.88,288.06;330.12,286.64;337.51,287.49;342.91,290.62;347.17,294.03;347.29,294.00;349.43,298.27;441.14,317.94;640.00,315.35;639.44,426.00;0.00,426.00" source="manual" z_order="0">
    </polygon>
    <polygon label="levee" occluded="0" points="344.45,296.56;346.80,299.55;348.51,302.33;350.22,305.54;351.07,308.96;352.57,312.17;354.28,314.95;358.13,314.73;361.76,314.73;365.18,314.73;367.96,316.87;369.24,320.50;370.31,323.71;370.31,327.34;370.31,330.77;370.31,334.61;369.89,337.82;369.67,341.03;372.45,342.74;375.66,342.31;379.08,342.31;382.29,344.02;384.42,346.80;385.71,349.79;386.77,353.00;388.91,355.78;392.12,356.42;395.75,357.06;399.17,357.27;402.38,357.06;406.66,355.56;410.29,353.64;413.71,352.36;417.34,351.29;421.62,350.65;424.83,350.22;428.67,350.00;432.31,350.00;436.16,349.79;439.58,349.58;443.21,349.36;446.63,348.72;450.48,348.08;453.69,347.87;457.32,348.08;460.96,349.36;464.16,350.43;467.37,352.14;470.79,354.28;474.00,356.20;477.63,358.13;481.26,358.77;485.33,358.77;488.75,358.13;492.38,357.49;496.66,356.85;500.29,355.99;504.35,355.56;507.77,354.92;511.19,354.07;514.40,352.78;518.46,351.50;522.10,350.65;525.30,349.79;528.72,349.79;532.14,350.22;536.20,351.50;539.20,352.78;542.19,354.71;544.76,357.06;546.04,357.91;550.10,356.63;553.31,355.78;556.73,354.71;559.93,353.64;563.78,352.78;568.27,352.14;571.91,351.72;575.54,351.50;579.17,351.29;582.81,351.07;586.66,351.07;590.08,351.07;593.92,352.14;596.92,353.85;598.41,356.85;600.12,360.05;602.48,362.62;605.90,364.11;609.32,364.76;613.16,364.76;616.59,364.76;620.43,364.97;623.85,365.82;627.27,366.25;630.69,366.47;634.54,367.11;638.60,367.32;640.00,367.53;640.00,367.53;640.00,366.04;640.00,295.92;347.01,295.71" source="manual" z_order="1">
    </polygon>
  </image>
  <image height="640" id="8" name="51096163559.jpg" width="427">
  <polygon label="sky" occluded="0" points="0.00,0.00;427.00,0.00;427.00,189.16;0.00,186.79" source="manual" z_order="-3">
    </polygon>
    <polygon label="sea" occluded="0" points="0.00,143.32;427.00,141.90;427.00,578.27;74.47,596.79;0.00,613.88" source="manual" z_order="-2">
    </polygon>
    <polygon label="breakwater" occluded="0" points="0.00,439.32;2.72,439.71;8.44,447.53;28.10,440.47;35.92,434.74;44.32,426.54;51.19,428.26;59.58,420.81;77.90,430.36;81.15,432.07;92.02,427.11;90.11,431.69;91.45,435.70;105.19,432.84;111.11,435.32;113.01,437.99;123.89,436.46;128.09,438.18;134.19,439.32;137.25,443.14;152.51,440.85;152.70,444.29;153.85,449.63;154.99,453.64;149.84,457.07;146.41,458.03;142.78,459.36;142.02,459.74;144.69,480.35;151.18,489.51;163.39,496.95;163.96,501.34;118.74,502.68;116.64,503.63;120.07,517.56;111.49,520.81;107.86,524.81;103.09,528.06;103.09,528.06;96.98,528.82;80.19,527.49;71.60,530.35;64.93,531.68;54.05,531.11;48.51,530.16;43.74,526.72;37.83,524.05;29.62,524.05;20.46,524.43;14.74,524.81;11.88,525.20;11.88,519.85;13.21,513.17;10.92,511.65;8.82,516.80;4.24,517.94;4.24,519.85;7.49,520.81;6.91,522.52;0.00,523.86;0.00,605.91;226.36,529.58;282.85,446.00;384.37,453.64;390.85,450.77;400.21,451.92;404.59,454.02;411.85,449.82;419.86,451.35;422.34,455.93;422.34,461.27;427.00,455.54;427.00,640.00;0.00,640.00" source="manual" z_order="-1">
    </polygon>
    <polygon label="levee" occluded="0" points="0.00,590.14;111.86,551.98;146.70,526.46;139.33,518.53;117.89,512.27;116.25,501.72;160.43,501.06;163.96,501.34;163.39,496.95;151.18,489.51;144.69,480.35;142.02,459.74;142.78,459.36;146.41,458.03;149.84,457.07;154.99,453.64;153.85,449.63;152.70,444.29;152.51,440.85;137.25,443.14;134.19,439.32;128.09,438.18;123.89,436.46;113.01,437.99;111.11,435.32;105.19,432.84;91.45,435.70;90.11,431.69;91.88,427.04;144.44,425.17;163.74,423.44;200.03,418.12;241.07,419.99;315.23,430.64;372.40,454.40;389.82,472.12;396.50,484.38;400.82,495.45;399.50,501.39;403.12,510.95;403.12,511.28;391.91,513.59;386.97,520.84;380.70,525.13;360.92,538.98;349.05,539.31;345.75,548.21;338.16,547.88;331.57,552.83;324.64,556.46;317.39,556.79;309.48,558.76;304.20,562.39;295.63,568.99;291.67,573.93;283.76,576.24;275.84,580.20;269.25,582.84;252.43,582.84;245.51,584.48;236.27,590.42;225.06,592.73;210.55,593.72;204.62,594.38;204.62,594.38;204.95,603.94;180.22,601.63;172.30,608.56;171.64,609.21;156.14,607.90;151.20,617.46;127.46,617.79;122.51,617.79;119.87,630.32;120.53,640.00;0.00,640.00" source="manual" z_order="0">
    </polygon>
    <polygon label="pole" occluded="0" points="379.21,484.74;375.40,484.17;375.97,481.69;379.41,478.82;380.17,439.51;376.73,439.13;376.16,419.10;379.02,418.52;379.98,386.47;379.02,386.08;379.02,380.55;377.88,378.64;379.79,376.54;379.79,364.52;375.21,363.95;369.86,366.81;370.44,354.03;374.44,356.32;373.87,351.93;376.54,345.25;379.41,345.06;380.36,342.58;380.55,340.67;381.89,340.67;382.46,342.39;384.18,343.34;383.98,348.68;385.51,348.87;385.32,354.98;389.71,357.65;389.33,359.56;383.22,359.18;383.41,360.13;387.61,361.66;390.28,363.38;389.52,364.33;383.60,364.14;383.79,367.96;395.43,368.15;398.30,367.19;397.72,366.24;398.11,358.22;401.16,358.03;402.49,362.80;401.54,367.00;404.98,369.29;404.98,371.39;405.17,374.83;401.73,374.44;400.40,372.73;403.64,370.25;399.25,370.82;398.49,372.54;395.24,372.15;395.05,370.63;389.71,371.01;387.23,371.77;383.79,374.06;383.79,375.02;385.89,378.64;383.41,380.17;384.37,418.72;387.80,419.29;388.56,438.75;384.18,438.94;384.94,466.42;386.08,478.44;382.46,480.73;382.27,482.26;383.60,483.21;382.65,484.55;381.12,483.79" source="manual" z_order="1">
    </polygon>
    <polygon label="fence" occluded="0" points="69.06,577.39;103.76,565.16;173.30,539.14;186.93,534.03;190.03,534.49;210.32,526.28;209.85,500.42;207.53,500.57;206.91,502.89;205.21,504.75;202.88,505.53;200.87,506.61;199.79,503.98;198.39,504.13;198.08,507.39;196.38,508.47;195.29,505.53;188.32,507.70;186.93,511.41;181.66,513.27;180.58,511.10;178.26,511.26;177.48,513.58;177.48,514.97;171.29,516.68;169.43,515.13;167.11,514.67;166.49,516.99;166.80,518.07;160.91,520.55;159.52,518.38;156.88,518.38;156.11,520.71;156.11,522.87;149.14,524.73;148.83,522.10;146.20,522.56;146.51,524.89;146.20,525.51;138.14,528.14;137.68,525.82;135.66,527.21;135.66,528.91;127.45,532.17;126.68,529.84;124.82,529.53;124.36,533.25;115.84,535.26;115.37,533.72;112.90,533.72;113.05,537.12;104.22,539.29;103.76,537.43;101.12,537.43;101.28,541.31;93.23,543.63;92.30,541.46;90.44,541.15;90.13,544.56;80.68,548.27;80.06,545.02;77.43,545.02;77.43,549.36;69.06,552.15;69.06,549.20;66.59,549.36;66.59,552.92;55.90,556.17;55.43,553.23;53.11,553.23;52.65,558.03;43.66,560.82;43.20,557.41;39.79,558.50;39.64,561.59;30.03,565.00;29.72,562.68;26.94,562.99;26.63,566.40;16.40,569.65;15.94,568.25;13.31,568.25;13.15,571.82;2.62,575.07;1.69,572.90;0.00,572.75;0.00,572.75;0.00,587.03;0.00,604.08;16.45,598.02" source="manual" z_order="2">
    </polygon>
    <polygon label="fence" occluded="0" points="198.80,406.50;228.50,409.70;251.50,412.80;285.20,416.50;297.70,418.20;309.00,419.90;318.00,422.20;324.80,424.30;331.70,426.20;338.00,428.20;358.20,435.70;373.00,443.30;380.70,449.60;386.70,453.70;388.00,454.70;388.70,456.10;389.00,457.80;389.50,459.50;389.80,461.10;390.20,462.70;393.70,487.30;393.80,490.50;393.50,492.20;393.20,493.70;392.80,495.20;392.00,497.00;391.20,498.50;390.20,500.10;389.00,501.60;388.00,503.00;386.70,504.20;385.50,505.30;384.20,506.40;383.00,507.60;382.00,508.80;380.70,509.90;379.30,511.10;378.00,512.10;376.50,513.30;375.20,514.20;373.70,515.10;371.80,516.00;370.20,516.90;368.70,517.60;367.30,518.60;365.70,519.50;364.00,520.30;362.50,521.00;361.20,521.80;359.50,522.70;358.20,523.60;356.70,524.60;355.20,525.80;354.00,526.80;352.30,527.50;350.70,528.20;349.20,528.90;347.20,529.60;345.70,530.00;344.50,530.90;316.80,543.60;284.20,557.30;218.80,584.00;164.10,607.40;161.60,606.20;160.40,603.80;153.30,606.70;152.50,611.90;149.90,612.60;148.70,608.40;140.60,612.60;140.60,617.10;137.60,618.30;136.80,613.80;127.80,616.60;127.80,618.70;124.20,618.30;113.90,622.90;114.00,628.70;109.50,629.70;109.40,624.10;100.20,628.60;100.20,633.70;95.70,633.70;95.90,629.00;86.60,634.50;85.90,640.00;81.80,640.00;81.40,635.90;69.90,640.00;11.00,640.00;22.20,636.50;22.00,633.40;24.10,632.60;25.80,633.60;37.80,628.80;37.60,626.20;40.30,625.50;41.10,627.80;53.60,623.20;53.30,620.60;56.00,620.10;56.50,621.80;67.90,617.40;67.80,615.90;68.40,614.40;69.90,614.20;70.70,615.70;70.80,616.70;81.90,611.40;81.60,609.90;82.20,608.30;84.00,608.00;85.40,610.10;96.10,606.30;96.00,602.70;99.10,602.60;99.10,605.00;109.20,600.70;109.60,597.50;111.60,596.90;112.20,598.00;112.30,599.90;123.00,595.70;122.60,592.20;123.90,591.70;126.00,594.30;135.90,589.80;135.90,588.00;137.00,586.90;138.10,588.20;138.10,589.90;148.90,585.40;148.60,583.90;148.00,582.20;149.50,581.70;150.50,582.90;150.60,584.40;150.70,584.90;160.70,580.40;160.90,578.80;162.00,578.40;163.30,579.80;172.70,575.80;172.90,573.50;174.90,573.30;175.30,575.00;183.70,571.80;183.70,569.40;186.90,569.20;187.10,570.70;196.50,566.80;196.20,564.90;198.50,564.80;199.40,565.80;208.10,561.40;208.10,559.70;210.40,559.60;210.50,560.00;219.00,557.10;218.70,554.70;220.10,554.10;221.00,555.40;221.00,555.90;229.30,552.80;229.70,550.00;231.60,549.90;231.60,552.00;240.80,546.60;253.60,542.30;283.40,529.90;317.40,515.50;345.20,506.00;364.20,495.90;380.60,483.80;380.60,471.40;379.70,469.10;378.10,467.40;376.10,466.10;374.10,465.10;371.70,463.80;369.50,462.90;366.90,461.80;364.90,460.50;363.00,459.30;360.90,458.20;359.00,456.80;357.00,455.60;354.70,454.50;352.80,453.30;350.50,452.70;348.10,451.70;345.90,450.90;343.40,450.40;340.60,449.80;338.30,449.10;323.70,442.80;306.70,438.60;304.10,438.50;302.00,438.30;299.70,438.00;297.50,437.70;294.60,437.30;292.30,436.90;290.20,436.50;287.60,436.20;285.10,435.70;282.80,435.30;280.70,435.00;278.20,434.70;275.60,434.30;273.30,434.10;271.20,433.90;269.00,433.60;266.80,433.30;264.40,432.90;262.10,432.30;259.80,431.80;257.30,431.70;255.20,431.30;253.00,430.80;250.70,430.40;248.10,429.80;245.80,429.40;243.70,429.10;241.20,428.80;238.80,428.50;236.50,428.10;234.30,427.80;232.10,427.70;230.00,427.40;227.70,427.10;226.50,426.90;226.20,422.30;198.90,418.30;195.40,414.30" source="manual" z_order="3">
    </polygon>
    <polygon label="lighthouse" occluded="0" points="140.00,420.28;144.35,348.61;150.53,266.17;148.24,266.63;147.78,262.28;136.33,261.59;137.94,240.06;151.90,239.15;154.42,238.69;154.19,223.81;153.05,221.75;165.87,204.11;165.18,199.76;168.39,192.43;168.39,191.06;170.45,191.29;170.22,192.89;173.66,200.45;173.43,203.88;186.02,222.89;184.65,223.81;184.65,235.26;186.25,235.94;191.52,236.17;199.08,235.26;207.32,256.78;203.43,257.24;203.43,261.82;189.23,262.28;199.76,403.79;201.59,420.51;200.45,422.57;181.67,423.49;161.75,423.94;148.24,422.80" source="manual" z_order="4">
    </polygon>
    <polygon label="fence" occluded="0" points="213.90,501.00;214.00,519.40;212.20,519.50;211.10,520.60;211.50,522.10;213.00,522.30;214.80,522.30;216.50,522.20;218.90,522.20;220.40,522.10;221.40,520.90;221.30,519.40;222.50,518.10;223.90,517.50;225.40,517.80;227.10,518.10;227.90,516.80;228.80,515.30;230.10,514.40;231.90,514.20;233.40,514.40;234.40,513.20;234.60,511.60;236.10,510.50;237.60,509.90;239.50,509.90;240.00,508.40;240.40,506.90;242.20,506.60;243.90,506.30;245.40,505.90;246.50,504.70;247.80,503.80;249.50,503.20;251.00,502.10;252.40,501.20;253.70,500.20;254.80,499.10;255.90,497.70;257.10,496.40;258.10,495.20;259.10,493.90;259.90,492.40;260.80,491.10;261.60,489.80;262.20,488.40;262.40,487.80;262.80,456.40;261.60,454.00;260.60,452.70;259.60,451.20;258.50,450.10;257.20,449.10;255.90,447.90;254.90,446.70;253.80,445.40;252.30,444.20;251.00,443.40;249.60,442.70;247.10,441.40;245.80,440.60;244.40,440.00;242.80,439.20;241.40,438.40;239.90,437.20;238.50,436.20;236.90,435.40;235.40,434.60;233.60,433.90;232.00,433.20;230.40,432.60;229.00,431.90;227.30,431.30;225.80,430.70;224.30,430.20;222.60,429.30;221.10,428.40;219.40,427.70;217.90,427.30;216.30,427.00;214.70,426.70;212.90,426.40;211.10,426.00;209.30,425.90;207.80,425.80;206.30,425.70;204.50,425.70;203.80,427.20;203.80,428.80;199.60,428.80;199.20,423.70;197.40,423.90;196.20,424.90;196.50,426.50;196.70,428.10;196.70,429.50;188.00,429.30;187.60,424.30;185.90,424.30;185.80,429.00;180.00,429.40;178.90,424.10;178.30,424.10;178.40,429.40;167.40,427.70;167.30,422.30;166.30,422.30;154.40,420.00;142.90,417.90;141.20,406.40;120.50,406.40;120.40,407.70;94.80,408.40;93.20,408.80;92.20,410.10;91.60,426.80;92.90,428.60;94.30,429.40;96.60,429.80;98.00,430.20;120.60,434.10;156.20,438.80;169.80,440.20;177.70,441.60;199.80,442.10;204.80,441.40;231.90,452.10;245.20,459.30;253.10,465.20;254.30,466.30;255.00,467.70;255.90,469.10;256.60,470.60;257.40,472.00;257.50,472.10;252.30,477.20;243.60,483.60;233.40,490.10;213.80,498.60" source="manual" z_order="5">
    </polygon>
  </image>
  <image height="427" id="7" name="51096084051.jpg" width="640">
  <polygon label="sky" occluded="0" points="0.00,0.00;640.00,0.00;640.00,254.19;0.00,229.58" source="manual" z_order="-4">
    </polygon>
    <polygon label="sea" occluded="0" points="0.00,207.32;640.00,208.55;640.00,427.00;0.00,427.00" source="manual" z_order="-3">
    </polygon>
    <polygon label="building" occluded="0" points="0.00,219.72;20.55,221.53;20.71,230.90;25.15,230.90;35.35,229.42;38.14,232.54;42.09,232.38;42.75,229.58;50.15,229.75;53.11,229.42;57.39,229.58;60.02,229.58;61.99,229.58;62.16,218.24;66.60,218.24;68.57,208.04;68.24,202.94;75.97,202.78;76.46,207.71;79.10,207.71;79.92,204.26;87.48,204.75;87.81,209.35;88.47,215.93;96.20,217.25;96.69,220.37;98.83,220.37;99.49,218.24;109.36,218.73;109.52,219.88;120.54,220.05;122.35,224.16;121.86,225.47;122.35,237.97;127.12,237.97;127.29,236.16;129.59,236.00;129.42,230.57;139.78,230.74;140.28,227.78;143.90,227.78;143.90,224.32;152.12,224.32;151.96,227.28;163.14,226.62;167.58,226.95;168.40,233.70;168.90,238.30;172.02,238.30;173.17,236.00;175.31,235.18;177.61,235.51;178.76,235.34;178.93,233.70;178.11,231.06;192.58,231.06;193.57,232.22;197.84,232.87;198.34,234.52;210.34,234.85;211.66,250.14;220.05,251.62;220.54,243.89;223.99,244.39;224.65,250.14;228.60,251.13;232.22,251.29;233.53,248.00;241.59,248.00;242.74,251.62;250.97,253.60;254.25,253.76;257.21,254.58;258.86,257.05;261.82,257.87;265.44,258.70;268.73,259.52;273.00,261.49;280.57,261.66;289.12,261.16;292.08,261.49;293.07,261.82;324.98,263.46;364.28,265.77;391.59,268.07;391.59,271.52;385.50,271.69;385.01,274.81;365.93,273.66;366.26,277.44;341.75,277.94;302.28,276.79;276.79,274.32;270.21,272.35;234.35,273.66;210.83,274.32;200.31,277.12;188.63,277.44;158.53,277.44;123.50,283.37;116.43,286.82;102.45,289.29;70.05,287.15;43.41,290.60;16.10,292.90;0.00,293.73" source="manual" z_order="-2">
    </polygon>
    <polygon label="road" occluded="0" points="195.88,272.14;280.90,270.48;305.54,274.51;305.54,283.98;189.72,283.98" source="manual" z_order="-1">
    </polygon>
    <polygon label="breakwater" occluded="0" points="0.00,293.40;48.19,290.33;70.70,286.92;104.12,289.31;132.09,285.90;146.75,284.19;173.35,281.46;213.60,280.78;264.41,281.80;290.67,279.08;337.39,280.44;366.72,280.10;366.38,273.96;384.80,275.33;385.82,272.26;391.96,271.91;392.30,266.80;427.43,267.14;428.79,269.53;438.34,270.89;450.28,275.33;453.35,279.08;499.73,280.44;537.59,278.74;562.82,279.42;573.05,277.03;579.53,278.74;595.56,276.01;597.61,279.08;600.68,278.39;605.11,279.08;607.84,281.46;609.55,284.19;613.30,285.90;616.37,286.58;621.14,288.63;622.85,289.65;614.66,289.99;613.98,292.72;613.64,293.40;600.00,291.69;589.42,293.06;572.71,293.06;568.62,294.42;562.82,294.08;555.66,295.11;552.25,296.13;547.48,296.47;544.07,296.81;544.07,296.81;496.32,296.81;466.99,295.45;447.55,296.13;423.34,298.17;395.03,298.17;349.67,297.15;324.09,299.20;318.30,299.54;310.45,297.49;287.26,298.17;243.61,299.88;210.53,299.20;187.00,299.54;187.34,301.59;193.82,303.29;193.82,304.65;177.11,304.65;167.22,304.65;160.39,302.61;155.28,301.93;150.16,300.56;141.98,301.93;137.20,302.61;131.41,302.61;124.93,303.29;119.81,302.95;111.28,303.63;106.85,303.29;100.71,305.34;93.89,305.34;89.12,305.68;85.02,306.02;79.23,306.70;73.43,308.41;68.31,309.43;73.09,311.82;76.50,316.93;76.50,318.30;67.97,317.27;70.70,314.54;68.65,313.86;59.79,314.20;51.94,315.57;45.46,315.23;39.32,315.57;34.55,320.34;29.78,323.07;24.66,322.39;19.54,322.05;14.09,321.02;13.75,320.68;0.00,321.71;0.00,310.79" source="manual" z_order="1">
    </polygon>
    <polygon label="lighthouse" occluded="0" points="410.22,269.54;421.11,269.54;417.79,242.30;421.35,241.83;420.87,238.75;419.45,238.04;417.79,233.77;416.37,231.64;412.82,232.12;411.16,237.33;409.74,238.04;409.51,242.30;411.87,242.30;409.51,265.04" source="manual" z_order="2">
    </polygon>
    <polygon label="fence" occluded="0" points="118.45,286.24;126.29,282.49;162.10,277.37;218.37,277.37;266.80,277.03;305.68,277.37;345.58,278.05;394.35,276.01;436.98,275.67;552.25,273.96;567.60,273.62;586.35,273.62;585.47,277.52;578.01,279.26;572.78,277.02;564.07,279.76;495.64,280.26;438.40,279.76;343.59,280.51;291.08,279.26;264.96,282.00;174.62,281.50;118.63,288.22" source="manual" z_order="5">
    </polygon>
    <polygon label="pole" occluded="0" points="481.71,280.08;480.89,256.89;483.85,257.38;483.85,268.56;484.35,268.73;484.02,273.17;483.19,273.33;483.52,280.57" source="manual" z_order="6">
    </polygon>
    <polygon label="lighthouse" occluded="0" points="563.68,274.35;574.93,274.55;573.75,247.31;576.00,246.68;576.00,242.14;574.60,241.55;573.24,238.39;569.21,234.09;566.05,238.63;565.66,241.59;562.90,241.99;562.90,247.12;565.07,247.71" source="manual" z_order="7">
    </polygon>
    <polygon label="pole" occluded="0" points="214.55,281.46;213.57,268.23;215.93,268.43;216.72,281.46" source="manual" z_order="8">
    </polygon>
  </image>
  <image height="425" id="6" name="51087870117.jpg" width="640">
  <polygon label="sky" occluded="0" points="0.00,0.00;640.00,0.00;640.00,358.40;0.00,343.97" source="manual" z_order="-4">
    </polygon>
    <polygon label="sea" occluded="0" points="0.00,324.09;261.68,324.09;640.00,322.73;640.00,425.00;0.00,425.00" source="manual" z_order="-3">
    </polygon>
    <polygon label="lighthouse" occluded="0" points="254.22,334.35;260.93,326.85;265.27,322.90;266.66,319.35;271.00,318.96;271.59,311.85;290.34,311.46;290.34,273.56;288.37,271.39;287.38,271.00;287.38,268.04;289.75,267.84;289.75,262.71;295.67,262.31;299.02,111.73;299.22,89.23;299.61,72.45;296.65,69.29;294.09,68.70;293.89,59.03;294.09,56.66;297.64,56.07;302.77,55.87;304.15,51.93;303.17,47.98;305.54,48.18;305.93,29.43;303.96,27.85;310.47,21.73;315.40,19.56;315.80,16.80;318.96,16.60;319.15,19.16;325.67,22.12;328.82,26.27;331.59,26.86;331.59,29.23;329.81,29.82;330.80,46.01;332.57,46.20;333.17,50.54;331.78,53.31;331.78,55.48;342.24,56.27;341.46,69.49;338.30,69.89;336.13,72.65;336.52,87.25;336.52,95.35;338.69,97.52;336.52,99.29;340.86,261.72;341.85,263.10;347.38,262.91;347.57,268.23;350.93,268.83;350.53,271.39;347.77,271.79;347.97,297.25;348.36,311.85;370.07,312.25;369.88,301.59;368.49,300.21;375.20,297.05;379.94,296.65;385.66,299.22;386.45,300.80;384.87,302.97;386.45,319.55;386.85,321.52;380.53,327.84;380.73,336.52;379.35,342.44;252.25,342.44" source="manual" z_order="-1">
    </polygon>
    <polygon label="terrain" occluded="0" points="78.17,362.85;69.41,362.85;65.62,362.38;64.20,362.14;64.44,360.48;72.73,359.30;79.36,352.90;82.20,355.27;87.17,355.27;90.96,354.80;92.62,355.98;100.20,356.93;100.91,354.80;109.44,352.19;118.20,351.48;121.75,351.95;125.54,352.90;127.91,354.09;129.57,355.74;137.86,356.69;140.46,354.09;143.54,352.19;147.33,350.06;150.65,347.22;155.15,345.56;158.94,344.14;159.88,344.14;161.78,346.98;166.75,346.51;169.59,346.98;173.15,348.40;177.41,348.64;181.67,346.74;184.04,345.56;186.41,344.38;189.25,342.96;191.14,341.30;193.99,341.30;196.59,340.35;199.91,338.69;202.28,338.22;203.46,335.85;206.54,336.32;210.80,337.27;213.64,337.03;216.25,337.03;218.85,336.32;221.46,335.38;224.06,333.96;226.20,334.67;227.62,331.59;230.46,332.77;232.83,333.25;235.91,333.72;238.51,334.43;240.88,333.25;243.01,334.43;244.91,332.53;247.27,332.77;250.35,334.43;252.96,334.43;254.38,334.67;255.80,338.22;259.59,338.69;267.41,337.51;279.25,337.51;286.59,338.46;288.96,336.80;297.25,336.80;303.17,336.32;309.56,336.09;313.59,334.67;318.32,334.90;321.64,335.85;325.19,334.90;328.27,333.72;331.35,332.77;334.90,335.14;339.40,333.96;344.61,333.48;348.40,333.72;351.48,333.72;355.51,334.67;359.53,335.38;362.61,336.56;365.45,335.38;368.77,336.56;371.38,337.98;374.93,338.46;378.01,337.74;379.66,335.14;380.85,333.01;386.30,335.85;392.45,335.38;394.82,333.48;396.72,335.38;399.80,334.90;404.53,339.64;404.30,341.06;407.14,342.96;411.64,343.67;415.66,344.85;418.74,346.03;421.11,346.74;431.53,346.51;437.22,352.19;460.19,351.95;463.50,350.06;478.66,350.53;493.82,351.01;496.90,351.72;499.50,350.30;502.82,348.88;506.13,349.82;509.69,350.77;512.53,351.24;523.90,351.24;528.16,350.77;529.82,357.17;525.79,356.93;522.24,358.59;522.24,358.82;518.21,359.30;508.98,358.35;493.58,360.01;489.79,359.77;489.79,359.77;451.90,360.48;423.95,361.67;364.51,361.90;298.90,362.14;220.04,362.85;178.83,363.32;136.44,362.85;110.86,362.61;91.44,362.38;82.67,362.14" source="manual" z_order="1">
    </polygon>
    <polygon label="boat" occluded="0" points="164.47,338.65;164.99,341.59;176.22,341.41;182.96,340.90;184.51,335.54;180.02,336.40;179.67,334.33;172.24,333.81;173.28,337.27;172.59,338.65;170.69,338.30;169.31,335.19;168.44,335.37;168.10,338.13" source="manual" z_order="2">
    </polygon>
  </image>
  <image height="639" id="5" name="51072675016.jpg" width="468">
  <polygon label="sky" occluded="0" points="0.00,0.00;468.00,0.00;468.00,456.98;0.00,460.92" source="manual" z_order="-2">
    </polygon>
    <polygon label="sea" occluded="0" points="0.00,417.22;468.00,421.02;468.00,639.00;0.00,639.00" source="manual" z_order="-1">
    </polygon>
    <polygon label="terrain" occluded="0" points="0.00,452.15;8.23,437.67;12.80,434.82;15.28,432.72;18.13,431.39;21.37,431.77;24.04,433.29;25.94,435.77;29.37,436.15;32.99,436.15;35.85,435.01;41.19,434.24;44.62,433.86;47.86,433.67;51.28,433.67;54.90,433.67;57.38,433.67;62.14,422.62;62.14,419.19;64.62,418.43;69.00,413.86;71.48,415.57;74.34,414.43;74.34,414.43;94.53,413.48;102.92,411.19;103.11,406.05;106.73,406.43;107.49,411.57;107.87,413.67;112.63,415.57;143.69,402.04;146.93,394.23;147.50,392.33;149.98,392.52;154.74,391.57;158.36,390.42;157.98,393.47;160.65,393.47;173.03,386.99;173.98,385.09;177.79,384.14;178.56,382.42;182.75,381.47;199.51,380.32;220.85,380.90;225.05,382.04;229.62,383.56;229.62,385.28;230.38,387.18;233.81,390.04;235.14,391.18;236.48,392.52;237.24,393.85;238.57,395.76;240.48,396.14;242.76,396.71;243.34,398.81;244.10,400.52;244.67,402.24;244.86,402.62;249.05,405.66;250.77,410.05;251.72,413.29;255.91,413.48;256.10,415.19;257.63,415.38;258.20,413.48;263.15,416.33;264.29,418.05;264.87,420.34;265.44,421.86;266.39,423.96;267.15,425.29;270.20,431.58;273.25,432.91;279.15,432.53;283.54,436.53;283.92,439.20;285.82,441.29;287.16,443.58;286.78,446.06;284.11,447.01;282.01,445.68;279.92,444.53;281.06,449.49;282.39,451.77;287.92,447.96;290.01,447.96;291.73,443.39;294.78,441.29;297.25,437.48;300.68,434.62;302.97,433.29;305.64,432.72;308.11,432.72;311.54,431.77;315.35,431.58;318.40,432.72;323.55,436.34;332.69,442.82;338.79,437.67;343.55,439.77;348.70,440.15;352.13,440.34;353.65,443.20;346.60,444.53;343.74,445.68;342.41,448.91;346.79,449.68;347.94,452.72;353.46,451.58;360.32,451.77;363.18,453.49;362.22,454.25;357.46,454.25;354.60,455.58;350.60,456.73;346.98,455.58;343.93,454.63;343.74,456.15;346.03,457.68;343.74,458.25;335.36,458.63;332.31,457.11;328.31,456.73;323.36,457.68;319.55,457.87;316.69,456.34;313.45,458.63;308.50,458.25;304.88,458.25;301.07,458.82;295.54,458.63;290.78,457.49;286.97,456.92;282.97,456.34;280.11,455.77;279.54,455.58;280.87,454.06;279.15,453.49;275.73,456.15;269.06,456.54;266.01,456.73;269.25,459.01;261.63,461.11;258.96,459.58;256.29,458.44;255.91,461.68;249.62,460.92;246.96,459.58;244.10,459.20;240.10,459.77;235.33,459.39;232.09,459.39;230.76,462.06;225.81,462.25;223.14,460.54;219.52,461.87;215.14,460.16;209.04,458.63;207.14,457.87;202.56,457.30;206.75,459.96;201.42,461.68;196.66,462.63;192.08,463.97;188.65,462.25;183.32,461.11;178.94,464.54;175.13,464.73;170.94,465.11;165.60,465.11;162.36,463.97;161.60,463.39;165.41,456.34;160.65,449.87;157.79,446.63;153.98,444.91;148.45,442.25;147.69,437.86;144.07,434.43;142.55,431.58;140.07,428.72;135.12,427.96;132.45,430.24;129.02,432.91;127.69,435.96;123.30,437.86;120.83,440.34;119.30,442.82;116.44,444.91;114.73,447.39;113.02,451.01;107.68,450.44;103.87,449.49;98.54,449.68;90.72,451.01;87.87,452.53;79.48,452.34;74.15,457.49;71.86,460.54;69.96,463.78;65.96,464.92;62.14,463.01;50.71,463.20;46.14,463.20;45.95,463.20;45.38,459.58;40.62,459.39;37.00,460.35;32.99,460.92;28.80,461.68;23.66,459.39;20.80,458.44;13.94,459.20;11.27,460.92;6.70,460.73;3.65,460.92;2.32,460.73;1.18,459.96;0.00,459.96;0.00,456.92" source="manual" z_order="0">
    </polygon>
    <polygon label="terrain" occluded="0" points="419.16,460.59;408.74,460.32;414.22,463.33;419.16,466.63;423.00,468.82;426.84,471.02;427.67,474.31;443.03,472.11;451.81,473.76;458.12,478.42;462.78,478.42;468.00,477.87;468.00,495.98;466.08,496.81;461.96,494.88;460.59,494.88;464.43,500.10;451.81,498.73;449.07,494.88;445.77,492.14;443.03,495.43;439.46,492.96;436.45,489.67;436.45,489.40;437.54,496.26;433.43,497.35;428.76,498.18;423.83,497.08;423.28,497.08;422.18,501.47;420.26,500.65;421.63,496.53;413.67,495.43;409.28,494.34;405.17,493.79;400.78,493.79;397.49,496.53;393.37,495.98;390.63,492.42;387.34,489.67;387.34,491.87;389.26,494.61;384.32,494.88;379.93,496.53;377.18,494.06;381.57,492.42;381.03,491.87;375.26,492.69;368.68,493.24;364.29,491.59;359.63,491.59;355.24,491.59;353.59,491.59;342.89,489.95;340.42,488.57;338.50,488.85;337.68,489.95;323.96,488.57;326.43,483.64;339.32,483.91;340.42,485.83;342.62,479.79;352.22,479.25;359.08,477.60;364.02,479.79;364.84,476.23;373.89,476.50;374.72,475.68;375.26,469.64;378.83,466.63;383.49,465.53;387.61,464.16;388.98,462.78;391.18,460.32;387.88,458.39;383.49,458.67;379.11,457.85;375.54,455.65;373.07,454.55;368.68,455.10;368.41,453.46;377.73,442.48;384.32,433.43;398.31,431.78;402.97,429.31;409.28,434.25;421.91,435.90;435.07,432.61;443.58,433.98;449.89,442.76;450.44,449.07;457.02,452.63;459.77,453.18;460.32,454.55;464.43,454.55;466.63,458.12;468.00,460.32;468.00,463.88;462.78,464.71;448.79,463.33;434.53,461.69;429.59,458.39;430.41,461.14;426.29,461.69" source="manual" z_order="1">
    </polygon>
    <polygon label="building" occluded="0" points="65.97,435.00;65.64,424.86;72.14,424.42;73.47,422.21;72.69,418.13;74.13,414.94;76.11,410.31;92.98,410.08;102.68,409.75;102.57,411.63;93.09,412.07;93.09,422.99;91.44,423.21;90.11,424.31;86.37,424.97;84.16,428.72;82.62,430.15;80.74,431.14;78.87,431.81;77.21,432.03;76.99,434.23;76.88,436.00;76.77,436.77;71.81,437.32" source="manual" z_order="2">
    </polygon>
    <polygon label="lighthouse" occluded="0" points="184.80,383.10;183.70,381.10;184.40,375.40;185.80,374.60;192.00,374.50;192.80,370.80;196.00,371.10;198.30,365.60;199.60,343.20;197.60,342.30;197.80,339.90;199.40,339.50;200.10,336.00;202.50,335.90;202.30,326.40;204.50,323.80;204.50,321.90;206.90,319.10;207.90,316.70;209.00,316.90;209.80,320.40;211.50,322.50;212.80,327.40;212.80,336.20;215.40,338.80;218.60,340.30;217.80,343.20;216.30,343.70;216.10,351.60;217.70,365.80;220.00,371.10;223.20,372.50;224.10,383.40;215.70,383.40;199.10,383.00;191.40,382.40;190.70,383.10" source="manual" z_order="3">
    </polygon>
  </image>
  <image height="640" id="4" name="51068067006.jpg" width="453">
  <polygon label="sky" occluded="0" points="0.00,0.00;453.00,0.00;453.00,470.01;0.00,471.43" source="manual" z_order="-15">
    </polygon>
    <polygon label="sea" occluded="0" points="453.00,417.99;139.31,413.41;0.00,460.35;0.00,640.00;453.00,640.00" source="manual" z_order="-14">
    </polygon>
    <polygon label="terrain" occluded="0" points="287.50,452.52;290.96,453.22;293.72,452.52;296.49,452.70;299.08,453.56;302.02,453.91;304.78,454.43;307.55,454.60;310.48,454.43;312.90,453.39;315.32,452.01;318.09,450.97;321.02,451.66;322.58,453.91;326.04,454.25;328.80,454.43;332.26,454.08;335.88,453.73;338.82,453.56;342.11,454.25;344.70,454.77;347.98,455.46;351.09,455.64;354.03,455.81;358.69,455.81;361.63,454.77;364.22,454.08;367.16,454.60;369.41,456.15;371.14,458.75;373.90,459.78;379.43,462.55;383.06,462.03;386.34,461.34;389.28,461.16;392.22,461.34;395.16,462.20;396.19,464.62;395.16,467.04;394.81,468.08;399.13,470.15;399.82,478.62;389.80,478.62;380.29,478.27;375.28,478.27;370.27,478.62;364.57,478.62;360.94,478.10;356.62,478.10;352.30,478.27;348.84,478.27;345.39,478.27;342.62,477.93;338.30,477.41;332.08,477.24;322.75,477.93;319.64,477.93;316.70,477.75;316.53,477.75;284.22,478.62;255.19,482.42;254.50,480.35;249.83,479.31;249.31,458.92" source="manual" z_order="-11">
    </polygon>
    <polygon label="levee" occluded="0" points="246.37,499.01;321.54,513.00;356.97,518.71;368.54,518.88;371.48,520.09;398.27,525.45;443.88,524.93;443.37,509.03;432.65,508.17;433.00,497.28;418.14,495.38;367.16,489.50;333.47,484.32;323.79,482.76;317.22,477.58;308.58,477.75;299.42,478.10;284.04,478.62;255.19,482.59;254.50,480.52;250.00,479.83;248.97,483.63;246.37,483.80;244.82,486.22;243.78,489.50;244.99,492.10;246.55,492.96;246.55,496.93" source="manual" z_order="-10">
    </polygon>
    <polygon label="shoreline" occluded="0" points="0.00,460.09;221.56,461.13;246.22,477.53;244.57,479.60;188.79,479.18;123.37,478.41;95.19,476.91;45.04,475.68;24.14,474.23;9.28,474.44;0.00,474.23;0.00,470.72" source="manual" z_order="-4">
    </polygon>
    <polygon label="building" occluded="0" points="0.00,400.80;16.00,401.60;20.80,397.30;21.30,401.30;34.20,400.90;35.00,396.50;37.00,396.50;37.70,393.10;42.00,393.30;42.20,395.80;45.00,395.70;45.20,393.90;47.30,394.10;47.60,395.70;55.30,395.80;56.70,398.60;80.40,399.60;83.00,397.60;88.00,397.80;88.70,395.00;98.00,395.10;98.10,398.70;101.40,399.10;101.40,402.20;103.90,402.50;109.10,401.90;110.70,400.40;115.30,403.90;115.20,407.10;116.80,409.20;117.10,410.70;119.50,409.90;121.20,410.90;122.50,409.20;124.20,408.90;125.70,409.60;126.20,411.40;126.30,412.00;128.60,411.90;138.00,404.30;140.70,406.40;140.90,403.40;141.90,403.80;142.10,407.80;147.00,411.10;151.90,412.20;169.50,412.20;173.30,414.00;181.00,413.60;191.20,414.20;191.90,412.60;196.50,412.50;196.90,414.70;199.20,414.70;199.20,412.30;208.90,412.10;210.60,414.00;214.60,412.50;219.10,413.00;218.80,414.50;218.90,415.30;222.20,415.80;222.70,412.00;229.80,413.10;229.60,417.20;232.90,417.70;234.40,423.00;234.80,427.10;236.10,428.40;273.20,431.00;274.60,447.30;277.00,450.80;286.70,451.20;286.70,455.20;288.80,457.70;289.40,460.00;294.30,461.10;296.90,461.10;299.60,461.30;302.10,460.70;304.40,459.20;307.40,459.40;310.00,459.80;312.70,461.80;313.70,464.30;314.80,466.70;315.60,468.90;312.60,468.20;313.00,472.20;316.40,480.20;317.80,482.80;318.20,485.90;316.60,488.50;314.50,491.30;311.90,493.80;308.30,494.50;303.80,494.20;300.90,493.20;299.70,492.80;299.20,480.50;299.30,473.60;293.80,465.70;285.50,464.60;283.60,464.30;278.10,466.50;273.90,464.30;270.60,462.40;267.90,462.40;265.10,465.20;265.10,465.50;254.90,463.30;252.30,462.90;253.00,466.20;253.40,471.70;252.00,479.90;234.00,476.90;226.20,473.80;218.50,469.50;218.30,465.90;207.40,464.30;203.20,464.10;199.40,465.30;197.40,467.10;193.50,469.30;177.30,469.50;165.90,470.30;150.70,468.80;145.20,465.80;130.50,465.80;119.10,466.50;114.80,469.80;107.90,470.30;103.90,469.30;98.40,468.30;95.50,461.60;83.00,460.50;41.00,460.50;12.70,461.20;0.00,461.60;0.00,439.50" source="manual" z_order="-1">
    </polygon>
    <polygon label="car" occluded="0" points="298.46,483.84;294.10,484.25;292.44,481.76;286.84,481.56;281.45,474.50;278.96,469.53;278.14,467.04;282.90,464.14;293.48,465.17;299.29,473.68;299.08,483.63" source="manual" z_order="1">
    </polygon>
    <polygon label="lighthouse" occluded="0" points="407.16,505.68;408.72,481.08;407.16,478.56;408.24,478.08;408.84,470.64;411.72,467.64;411.96,464.40;414.36,464.64;414.36,466.68;416.64,469.44;416.52,476.40;419.28,477.72;419.28,480.60;416.76,480.84;417.36,495.24;419.76,496.68;420.00,502.80;419.64,506.52;415.32,506.52;415.08,504.36;412.32,504.48;411.72,506.52" source="manual" z_order="1">
    </polygon>
    <polygon label="car" occluded="0" points="323.84,493.64;320.52,493.02;317.20,492.40;314.09,491.16;311.81,488.88;311.60,485.76;314.92,484.31;318.03,483.69;320.31,483.90;324.67,485.14;332.34,486.59;337.11,488.67;340.22,490.95;353.28,489.91;356.81,493.64;358.26,497.79;347.68,498.21;341.67,497.38;340.43,495.72;331.51,495.51" source="manual" z_order="2">
    </polygon>
    <polygon label="boat" occluded="0" points="81.76,491.49;73.47,490.97;72.26,482.85;79.52,482.68;81.25,485.96;87.99,485.27;91.44,489.24;90.75,491.49" source="manual" z_order="3">
    </polygon>
    <polygon label="boat" occluded="0" points="58.78,486.13;51.87,485.62;52.04,481.47;59.30,481.81" source="manual" z_order="3">
    </polygon>
    <polygon label="boat" occluded="0" points="31.13,485.96;24.57,485.10;23.19,482.16;29.75,480.95;36.49,480.95;36.32,484.75" source="manual" z_order="3">
    </polygon>
    <polygon label="boat" occluded="0" points="14.13,490.54;2.55,487.95;5.32,483.28;5.32,479.48;14.30,480.00;15.69,488.47" source="manual" z_order="3">
    </polygon>
    <polygon label="car" occluded="0" points="405.45,505.19;390.94,503.33;382.85,502.91;378.50,500.22;379.95,495.45;390.73,496.90;401.72,497.73;406.49,501.88" source="manual" z_order="3">
    </polygon>
    <polygon label="boat" occluded="0" points="39.95,495.12;30.79,494.77;29.41,492.36;37.18,490.97;40.47,491.49" source="manual" z_order="3">
    </polygon>
    <polygon label="boat" occluded="0" points="73.99,496.67;60.86,495.81;62.93,490.97;73.13,491.66" source="manual" z_order="3">
    </polygon>
    <polygon label="boat" occluded="0" points="182.09,503.61;164.18,502.86;164.18,497.64;156.46,496.89;150.99,496.39;136.31,494.90;136.81,488.93;132.08,486.44;135.06,481.46;144.27,482.21;147.01,485.94;152.73,486.19;154.72,480.97;163.68,478.48;169.15,484.20;169.90,486.94;180.10,488.68;187.32,486.94;188.56,492.41;183.34,492.91" source="manual" z_order="3">
    </polygon>
    <polygon label="boat" occluded="0" points="111.31,496.33;100.95,496.50;98.35,490.97;98.53,486.31;92.48,486.13;92.82,483.02;102.50,480.95;105.96,483.72;112.52,485.10;116.15,484.06;119.44,488.04;118.92,492.18;113.56,492.36" source="manual" z_order="3">
    </polygon>
    <polygon label="boat" occluded="0" points="253.24,511.22;235.32,509.79;225.29,504.42;208.45,502.62;203.43,497.61;202.00,493.67;207.37,492.95;209.52,491.16;208.09,489.01;212.03,485.43;212.39,481.13;218.12,481.48;224.21,484.35;233.89,485.07;239.26,486.50;238.54,491.52;229.23,490.80;230.66,496.53;235.32,497.25;239.98,491.52;244.64,499.76;246.79,502.27;254.67,505.49" source="manual" z_order="4">
    </polygon>
  </image>
  <image height="480" id="3" name="51019323981.jpg" width="640">
  <polygon label="sky" occluded="0" points="0.00,0.00;640.00,0.00;640.00,236.38;0.00,214.68" source="manual" z_order="-4">
    </polygon>
    <polygon label="sea" occluded="0" points="0.00,194.27;271.20,194.70;640.00,190.43;640.00,480.00;0.00,480.00" source="manual" z_order="-2">
    </polygon>
    <polygon label="lighthouse" occluded="0" points="276.27,223.74;275.23,166.54;272.99,165.85;273.16,164.99;273.16,152.37;284.91,152.03;285.43,146.67;287.67,146.84;288.36,152.20;293.38,153.06;292.68,163.95;291.65,184.17;292.34,224.08;278.00,225.12" source="manual" z_order="-1">
    </polygon>
    <polygon label="terrain" occluded="0" points="0.00,201.08;24.47,198.50;51.38,189.63;68.84,184.48;91.74,182.19;98.32,180.76;113.92,181.19;125.23,181.90;141.40,184.48;154.71,193.06;167.02,198.36;179.18,202.80;185.34,205.09;196.21,204.51;210.95,210.10;235.86,218.83;248.45,222.83;259.61,223.98;272.50,222.98;274.93,224.55;286.38,219.97;287.38,222.98;292.10,222.69;296.68,224.26;307.99,220.83;321.73,219.68;340.76,220.26;366.24,221.12;376.69,234.43;382.12,240.01;384.41,241.01;387.13,248.74;385.56,251.46;352.93,255.75;339.19,257.18;335.75,257.04;332.75,257.18;329.46,257.18;326.59,257.18;322.87,258.61;320.73,260.19;320.15,260.33;306.70,259.33;297.83,258.76;305.56,271.21;305.99,274.93;309.28,275.50;309.42,290.67;306.27,298.69;304.70,306.99;300.83,309.13;298.69,308.85;297.25,315.29;296.40,318.01;294.82,320.30;292.96,322.30;292.53,325.88;291.10,328.17;289.24,330.74;287.52,334.75;287.24,339.76;287.52,342.48;286.38,348.49;286.23,352.64;286.09,356.79;285.95,359.94;285.23,365.67;284.80,368.53;283.80,370.96;280.65,379.12;279.79,385.56;282.23,389.57;289.53,394.00;296.83,395.86;327.88,395.86;342.77,404.59;350.35,407.03;364.95,416.04;368.96,418.62;373.11,422.91;377.26,426.20;381.98,430.07;383.56,430.93;385.99,434.79;387.99,438.66;404.74,454.26;420.19,466.14;430.36,472.72;435.22,476.30;439.66,477.44;443.24,480.00;443.52,480.00;444.09,480.00;0.00,480.00" source="manual" z_order="0">
    </polygon>
    <polygon label="person" occluded="0" points="81.70,272.29;97.77,272.12;99.84,270.74;97.94,269.18;91.89,268.15;90.51,265.90;90.51,263.83;90.16,256.74;90.68,253.11;91.37,250.00;91.89,247.41;92.93,244.65;93.62,241.54;93.96,238.77;94.48,236.18;94.83,235.14;99.15,233.76;96.21,224.08;95.35,214.58;94.83,213.89;95.69,209.91;100.36,212.16;104.16,209.22;103.64,206.46;103.30,204.56;100.19,199.55;99.49,196.95;99.32,194.36;97.59,192.29;97.59,192.12;97.59,188.49;93.96,188.83;94.66,192.12;93.62,194.88;89.82,187.62;85.84,182.09;82.73,181.23;76.51,182.09;73.06,184.86;73.40,189.52;75.99,193.84;76.86,196.78;73.06,199.89;74.44,206.80;77.38,212.33;76.68,214.92;77.55,216.13;78.59,215.79;78.76,217.00;76.68,218.21;68.22,218.90;68.04,222.18;66.32,225.81;69.43,228.23;76.51,228.92;77.38,232.72;79.45,236.52;79.45,247.41;76.68,251.73;77.38,256.74;76.34,258.82;78.24,265.38;76.34,271.60" source="manual" z_order="1">
    </polygon>
  </image>
  <image height="445" id="2" name="51007977248.jpg" width="640">
  <polygon label="sky" occluded="0" points="0.00,0.00;640.00,0.00;640.00,184.60;0.00,177.00" source="manual" z_order="-2">
    </polygon>
    <polygon label="sea" occluded="0" points="0.00,200.04;179.90,200.53;316.43,201.02;426.92,199.05;558.54,199.05;640.00,198.07;640.00,445.00;0.00,445.00" source="manual" z_order="-1">
    </polygon>
    <polygon label="breakwater" occluded="0" points="109.56,253.43;113.90,253.04;116.07,250.87;119.23,250.67;122.58,251.26;125.54,251.06;128.70,251.46;131.86,250.47;134.82,250.87;136.79,253.23;139.75,254.02;143.30,254.22;146.07,255.41;149.62,255.41;153.57,255.80;157.32,256.59;160.67,256.39;163.83,256.79;174.29,251.66;179.42,250.47;183.17,250.87;185.74,253.04;188.50,255.41;191.66,255.41;194.82,254.42;196.39,251.46;198.17,248.89;201.72,250.47;204.49,252.05;207.64,253.04;212.38,253.63;215.93,254.42;218.89,254.22;223.04,252.64;225.01,249.68;227.58,247.71;230.74,248.89;230.14,252.05;237.25,252.45;241.20,251.46;244.55,250.67;247.91,252.05;250.47,250.27;252.64,247.31;256.79,250.27;259.55,252.05;263.69,252.25;266.66,252.64;269.62,249.29;272.58,251.46;272.38,254.42;272.77,256.98;272.58,259.75;272.58,260.54;278.50,258.37;282.44,257.38;285.01,259.16;288.17,258.76;292.90,257.77;296.26,257.38;298.63,258.76;302.18,258.17;310.67,258.37;316.19,257.97;320.34,257.77;323.89,257.58;325.27,257.58;349.55,257.18;352.31,257.58;355.07,258.17;361.39,257.18;369.28,257.18;372.24,260.14;373.03,262.12;373.03,262.71;378.36,259.16;383.49,260.73;388.23,261.33;390.60,261.92;392.77,263.69;393.76,266.66;393.16,271.19;394.35,274.16;400.27,270.41;404.41,270.60;405.01,272.97;408.56,269.62;413.89,272.58;419.22,276.13;425.14,278.50;427.70,279.09;430.86,279.29;432.83,279.68;439.15,279.09;440.93,282.44;443.69,283.43;445.66,284.81;446.45,286.98;446.25,288.96;448.82,291.13;450.79,290.73;454.15,293.30;455.93,294.68;457.70,293.30;459.67,294.29;462.24,295.27;465.60,294.29;470.53,294.68;473.29,294.88;473.49,294.88;474.48,300.21;459.48,300.21;458.10,302.38;435.79,303.17;410.14,304.15;367.31,304.15;342.64,304.75;302.18,302.97;269.02,302.38;244.35,301.59;220.28,300.40;205.87,298.63;178.24,296.65;159.29,294.88;146.26,294.29;133.83,294.68;90.81,274.55" source="manual" z_order="0">
    </polygon>
    <polygon label="lighthouse" occluded="0" points="325.29,256.79;327.28,201.09;325.29,198.53;325.86,192.57;328.98,190.58;329.55,182.05;327.56,181.77;333.53,173.81;336.09,154.48;338.36,154.77;338.08,174.09;344.33,181.20;342.34,181.48;342.62,190.29;344.04,190.58;344.04,192.57;347.74,192.57;346.89,199.67;345.75,201.66;346.60,257.36;325.29,257.65" source="manual" z_order="1">
    </polygon>
    <polygon label="boat" occluded="0" points="0.00,342.17;50.58,346.26;122.20,341.83;141.64,337.05;193.13,335.35;219.74,333.64;220.08,325.80;226.56,322.05;229.28,316.93;226.90,314.54;224.85,314.20;224.85,312.16;222.80,311.13;221.44,312.16;219.74,311.13;216.67,312.84;215.98,312.50;214.96,308.75;210.87,305.68;205.75,303.29;201.66,303.63;198.59,303.97;196.54,305.68;195.52,308.06;194.50,310.45;193.13,311.82;193.48,300.22;190.41,298.86;186.65,298.52;184.27,297.15;181.54,296.81;178.81,297.83;176.42,298.52;174.72,298.52;173.69,232.35;164.83,223.49;164.83,284.19;164.83,312.84;153.91,313.18;146.41,311.13;153.57,301.24;161.76,283.17;164.83,272.60;164.83,271.91;162.44,272.94;157.67,287.26;151.19,299.88;146.41,307.38;141.30,311.13;139.25,312.16;137.89,311.13;138.23,257.25;117.76,256.23;110.26,255.89;111.28,231.67;118.45,232.35;120.49,229.28;125.27,228.26;124.93,224.85;106.51,223.49;96.96,222.46;89.12,223.49;88.43,221.10;84.00,221.78;73.43,222.12;72.75,196.20;70.36,196.20;70.70,222.46;65.24,221.78;54.33,206.78;44.78,198.93;31.48,197.57;31.48,194.50;33.87,192.45;34.55,185.29;37.96,184.61;38.30,180.17;36.94,174.72;34.21,174.72;33.19,180.17;30.80,180.17;30.80,184.27;18.18,184.27;16.82,189.38;18.18,191.09;25.00,191.77;25.34,198.59;19.54,197.91;18.18,195.86;16.13,195.86;15.79,198.25;7.61,198.93;5.22,201.66;3.86,209.50;0.00,209.50;0.00,252.48" source="manual" z_order="2">
    </polygon>
    <polygon label="boat" occluded="0" points="521.60,219.94;552.16,219.80;551.75,218.43;548.87,218.15;548.60,214.32;542.57,214.04;542.29,215.00;526.81,214.86;526.53,217.74;521.87,217.74" source="manual" z_order="3">
    </polygon>
  </image>
  <image height="424" id="1" name="50937411946.jpg" width="639">
  <polygon label="sky" occluded="0" points="0.00,0.00;639.00,0.00;639.00,230.42;0.00,222.29" source="manual" z_order="-10">
    </polygon>
    <polygon label="sea" occluded="0" points="0.00,208.25;141.57,207.76;277.39,214.14;332.31,271.02;639.00,345.06;639.00,424.00;0.00,424.00" source="manual" z_order="-9">
    </polygon>
    <polygon label="vegetation" occluded="0" points="135.96,210.60;146.67,202.66;147.19,199.20;147.88,196.61;150.47,196.95;152.03,194.36;154.44,193.32;157.73,193.15;160.15,191.77;161.53,189.52;161.70,189.35;163.26,189.70;163.43,193.15;164.29,192.81;164.64,190.39;167.23,191.25;169.31,189.35;171.03,191.42;173.80,191.08;175.53,189.00;175.87,188.66;177.77,191.25;179.16,188.66;182.44,191.94;202.83,190.73;208.01,190.91;223.22,189.70;243.78,188.83;248.79,188.31;253.29,186.93;265.90,187.80;269.18,187.45;274.37,186.24;277.65,186.41;280.76,186.41;284.22,186.41;288.88,186.41;291.99,186.41;298.56,185.03;301.84,185.55;304.44,186.07;307.72,186.41;311.17,185.03;314.28,185.55;317.05,185.55;318.26,185.89;326.04,186.59;330.70,186.24;333.64,185.55;337.09,184.68;339.51,185.89;341.76,184.34;344.52,184.17;347.12,184.51;349.88,184.86;352.13,186.41;353.68,183.99;356.97,184.68;359.39,185.89;362.15,186.07;365.26,185.55;368.03,184.68;370.79,184.34;373.90,185.20;376.67,184.68;379.95,183.48;382.54,184.34;384.79,181.92;387.38,182.78;390.32,181.06;392.91,180.02;395.33,180.54;397.40,178.98;400.17,178.98;402.59,179.67;406.39,178.98;408.81,178.81;410.53,179.67;539.62,176.04;542.21,176.39;542.55,178.64;543.76,179.85;544.80,178.81;544.80,176.22;548.60,178.12;551.19,177.95;553.79,177.60;556.55,177.60;557.41,175.01;559.49,177.77;561.91,176.04;564.84,175.35;567.44,177.60;571.24,177.25;572.79,174.84;575.39,172.93;576.25,172.76;579.53,171.55;579.88,168.10;581.09,164.81;581.61,162.22;576.25,156.69;575.39,153.75;574.35,150.47;579.01,149.26;579.88,146.15;579.53,139.76;580.74,135.09;581.26,133.54;583.51,136.30;585.93,135.26;589.21,133.36;591.97,131.81;594.57,129.91;597.50,129.39;600.27,130.08;602.34,130.08;608.39,134.75;609.08,130.25;610.64,125.76;613.23,128.35;619.80,129.73;624.98,130.77;628.78,131.12;632.41,131.64;635.00,130.94;635.69,128.01;639.00,126.97;639.00,127.14;639.00,361.46;187.97,266.25;195.23,242.92;200.76,243.96;199.03,240.15;201.96,239.81;203.52,237.39;206.80,238.60;210.78,239.46;213.37,239.12;215.27,238.94;217.17,239.81;217.34,237.04;217.00,234.80;218.90,233.76;221.32,235.66;224.43,235.49;226.85,234.62;228.75,235.83;235.83,235.49;237.91,235.49;241.71,236.18;245.51,236.52;248.62,236.70;250.87,236.70;251.39,236.52;259.33,219.59;260.20,210.95;173.80,208.36;160.67,213.37;141.14,212.51;136.65,211.81" source="manual" z_order="-6">
    </polygon>
    <polygon label="shoreline" occluded="0" points="158.02,212.59;163.78,208.13;164.64,206.11;166.08,203.66;167.66,202.08;170.26,200.93;172.70,200.35;175.01,200.50;175.01,202.94;177.02,203.95;179.18,203.66;181.06,201.94;183.94,201.79;186.38,204.10;188.54,204.82;190.70,205.82;193.15,205.97;195.60,206.40;192.86,203.38;190.99,201.79;190.70,201.65;198.48,200.21;200.93,199.34;203.09,199.06;205.97,199.49;208.13,199.34;210.86,199.34;213.74,199.49;216.48,199.20;218.64,198.62;220.94,198.34;223.10,197.90;225.41,197.62;228.86,197.33;231.02,197.62;236.21,197.62;239.38,197.47;242.11,197.04;244.85,196.61;247.44,196.18;249.74,195.89;252.34,195.74;254.21,195.74;275.52,199.20;284.59,198.48;285.46,195.89;288.05,197.47;292.22,196.90;296.26,197.04;298.85,199.20;302.16,198.91;305.33,199.34;308.78,199.78;312.38,199.34;315.26,198.19;318.00,197.47;326.21,195.46;328.37,196.46;325.78,197.33;323.33,199.34;327.07,203.38;337.73,203.66;344.78,202.22;345.94,200.64;353.86,199.78;359.04,197.33;361.49,196.18;364.37,195.31;365.81,194.74;367.68,194.45;370.42,194.59;372.00,195.02;372.72,197.18;373.30,198.62;382.37,200.21;381.22,200.93;376.03,201.65;374.88,200.06;373.58,200.06;370.85,203.09;366.67,202.37;364.37,202.08;363.36,204.53;363.07,206.69;361.06,207.55;357.17,205.25;354.00,203.23;349.97,203.23;346.22,203.38;343.34,203.81;340.90,204.53;341.18,207.41;339.74,209.28;336.58,208.56;334.42,207.12;332.26,207.26;329.23,205.97;326.93,206.83;325.20,206.54;312.96,207.12;252.62,222.38;236.78,222.24;210.72,222.24;185.38,221.66;185.81,219.36;196.18,219.36;210.58,218.35;202.37,216.62;174.86,215.18;161.33,214.03" source="manual" z_order="-5">
    </polygon>
    <polygon label="building" occluded="0" points="251.17,237.54;251.17,218.99;247.73,218.99;252.16,203.55;252.82,203.88;252.16,196.33;253.64,191.57;274.16,191.40;276.63,198.46;274.82,198.96;274.99,203.55;275.48,203.55;275.64,202.24;277.12,202.40;277.12,203.39;287.79,203.72;287.63,203.06;285.82,202.90;286.32,200.27;293.38,199.78;294.36,202.57;292.88,203.06;293.21,203.55;308.32,203.88;318.67,204.05;318.83,177.94;320.47,176.62;324.25,176.62;325.40,178.76;325.23,207.33;330.65,219.97;327.37,219.97;327.37,225.23;326.38,226.05;314.23,225.23;312.26,226.38;310.62,227.20;305.04,227.04;303.23,227.04;300.93,227.69;298.96,228.02;297.97,229.66;298.14,230.98;291.41,229.83;291.73,231.96;290.75,234.10;288.12,234.10;285.82,234.10;283.36,233.93;281.55,233.77;279.75,233.93;278.11,234.92;275.81,234.75;275.64,236.56;275.15,238.37;273.34,239.19;271.54,239.52;269.24,239.52;267.43,239.35;265.79,238.53;263.65,238.69;261.36,237.22;259.06,236.07;256.92,236.72;254.62,238.20;253.80,239.19;251.17,238.86" source="manual" z_order="0">
    </polygon>
    <polygon label="levee" occluded="0" points="448.95,424.00;378.00,405.09;336.29,390.90;269.65,361.66;239.12,350.48;233.96,346.18;222.78,343.60;209.45,334.14;198.27,325.54;192.25,324.68;184.94,320.38;172.90,308.77;169.46,304.47;162.58,299.31;156.56,296.31;150.11,286.42;141.94,274.38;141.51,267.50;151.83,258.47;161.29,251.16;163.01,252.88;190.10,244.71;199.13,243.85;201.71,249.44;197.41,252.88;196.55,258.47;197.84,263.63;201.71,266.64;207.30,266.64;212.89,267.50;213.75,267.50;221.49,267.07;261.05,263.20;284.70,260.62;317.37,255.89;355.64,250.73;392.62,247.29;401.65,246.86;483.78,255.46;521.19,256.32;522.48,252.02;569.77,270.94;605.03,285.99;626.10,296.74;629.11,296.74;639.00,304.04;639.00,424.00" source="manual" z_order="6">
    </polygon>
    <polygon label="building" occluded="0" points="416.24,251.90;401.38,251.73;400.68,237.39;398.61,237.04;398.61,227.02;401.03,227.02;401.20,210.43;397.75,209.57;397.23,203.87;415.20,172.59;456.15,152.54;457.71,152.54;458.23,143.39;467.39,144.42;467.56,155.31;487.43,159.63;487.95,141.31;497.28,142.00;497.28,161.70;504.36,163.78;534.95,162.39;540.65,185.20;538.06,185.38;537.37,194.53;543.94,205.77;540.31,209.74;540.48,211.99;542.04,212.68;544.11,215.96;544.28,218.38;548.08,224.08;560.35,224.60;561.22,222.36;566.92,222.36;566.75,220.80;572.10,220.80;572.28,222.70;602.69,222.87;606.49,233.76;605.80,240.15;602.86,236.70;599.23,234.11;594.74,234.80;592.49,235.32;590.94,236.01;589.56,237.04;587.14,237.04;585.75,236.52;584.20,237.22;583.16,238.60;582.64,239.98;581.09,240.50;579.36,240.67;577.80,241.54;576.60,241.71;567.78,241.19;565.19,240.33;557.93,241.36;557.41,244.13;547.74,244.82;541.69,245.34;538.23,245.68;523.72,252.94;518.88,256.22;460.82,253.80;453.73,253.11;433.34,250.52" source="manual" z_order="7">
    </polygon>
    <polygon label="lighthouse" occluded="0" points="416.21,260.40;417.65,262.27;432.05,262.42;442.85,260.69;453.65,255.79;453.65,232.61;453.36,180.05;453.50,159.46;456.38,155.28;457.25,141.89;451.92,140.02;447.89,139.87;448.03,125.90;435.22,117.41;435.22,116.11;436.51,114.24;435.50,111.94;434.35,111.50;434.06,102.43;432.77,102.43;432.91,111.36;431.33,112.51;430.75,113.23;430.61,114.67;431.76,114.96;431.62,117.84;429.31,119.71;422.26,123.89;418.51,126.91;419.81,128.64;419.66,140.45;411.89,141.74;410.45,143.18;411.46,155.57;415.63,160.46;415.92,187.25;416.06,221.23;415.92,246.29;415.49,256.66" source="manual" z_order="8">
    </polygon>
    <polygon label="pole" occluded="0" points="578.06,249.10;578.06,203.57;579.30,192.37;577.31,193.12;574.33,189.63;576.07,178.69;577.81,155.29;578.56,151.81;580.30,152.31;581.54,250.60;579.06,249.85" source="manual" z_order="9">
    </polygon>
  </image>
  <image height="640" id="0" name="50873352763.jpg" width="640">
  <polygon label="sky" occluded="0" points="0.00,0.00;640.00,0.00;640.00,174.10;0.00,157.09" source="manual" z_order="-3">
    </polygon>
    <polygon label="building" occluded="0" points="429.60,94.92;430.80,94.32;431.04,84.24;434.16,84.36;436.92,81.48;437.88,79.92;439.80,79.80;442.08,79.92;444.00,80.04;447.48,79.68;449.28,80.04;451.20,80.16;452.76,81.48;454.92,81.24;455.88,80.04;458.88,73.92;458.76,67.92;459.84,68.04;460.56,74.88;463.08,82.56;465.48,83.04;466.80,84.84;466.68,87.00;466.68,87.00;470.04,86.76;470.64,89.28;471.84,89.28;472.08,87.60;474.72,88.32;475.32,92.76;477.72,92.16;480.48,92.40;482.64,92.64;483.72,94.32;485.88,95.28;486.48,97.56;486.48,97.56;492.00,97.08;492.96,94.80;495.24,95.40;495.96,96.84;496.68,94.68;498.48,89.76;500.76,90.60;500.76,93.12;501.24,95.28;502.80,96.96;503.40,97.80;502.68,99.96;504.36,107.04;503.88,111.60;503.76,118.44;502.32,121.68;492.72,125.16;467.16,127.08;431.04,102.48" source="manual" z_order="-2">
    </polygon>
    <polygon label="vegetation" occluded="0" points="0.00,111.12;5.54,110.78;8.64,110.78;8.75,108.91;10.62,109.02;12.39,109.57;14.05,110.01;15.70,109.68;17.69,109.79;18.91,111.01;20.78,110.67;22.44,110.78;24.76,110.56;26.53,110.56;30.28,110.89;31.94,110.67;33.70,109.68;35.47,110.45;37.57,110.45;39.56,110.45;41.32,110.23;42.98,109.79;44.64,110.34;47.07,109.79;48.83,110.12;51.48,110.56;53.25,111.01;54.91,111.67;56.78,112.22;57.34,110.34;58.66,109.13;60.32,109.68;60.87,111.34;62.53,112.00;64.18,111.45;65.51,110.34;67.38,109.46;69.26,109.68;71.03,109.46;72.58,110.12;73.79,108.80;75.78,109.68;77.54,109.35;79.09,108.13;80.86,108.58;82.62,108.91;83.95,110.01;84.72,111.67;86.49,111.67;86.16,109.57;88.15,108.91;89.25,110.56;91.13,110.67;93.00,111.23;95.10,111.78;96.10,110.45;96.87,108.47;97.86,107.14;99.41,106.26;101.07,106.81;102.72,106.59;104.60,107.91;106.26,107.91;107.69,107.36;109.02,106.48;110.23,107.91;111.78,108.58;112.22,106.81;113.21,105.48;114.98,106.81;115.97,108.02;117.19,109.13;120.06,108.80;121.39,108.02;122.71,108.80;123.26,107.36;124.26,106.04;126.36,106.26;128.12,107.36;129.89,107.58;131.55,107.14;133.64,107.58;137.62,107.80;139.94,106.81;141.59,105.93;142.92,105.26;144.58,104.49;146.23,103.94;147.67,105.48;148.55,107.03;149.88,107.80;150.98,109.02;152.42,107.58;154.07,107.58;154.74,109.13;157.06,109.13;159.93,109.46;161.47,108.69;163.46,108.47;165.12,108.58;170.86,108.47;176.27,109.35;179.80,109.90;181.68,109.02;183.89,109.35;186.87,109.24;188.20,107.91;190.41,107.36;191.95,108.35;193.50,109.35;196.59,109.13;199.02,108.91;202.77,108.69;205.20,108.69;206.75,107.14;206.75,105.26;207.96,102.17;210.06,102.83;212.27,102.61;214.70,103.72;214.48,106.26;217.24,106.81;219.34,106.70;219.78,106.70;226.52,106.59;228.28,106.37;228.72,104.60;229.83,103.28;230.82,104.82;232.04,103.72;232.81,102.17;233.92,101.07;234.69,103.05;236.46,103.94;238.33,105.15;242.31,105.26;244.07,104.27;244.96,102.50;246.95,102.39;247.28,104.38;249.71,104.38;252.58,104.71;260.31,104.49;266.05,104.38;269.69,103.39;276.10,103.83;279.52,104.71;289.90,104.71;291.01,102.39;292.89,102.39;294.32,103.61;295.98,102.61;297.41,102.39;298.52,103.39;299.95,102.72;305.36,103.39;308.79,105.15;311.77,104.16;315.08,103.94;319.06,104.16;323.14,104.16;326.24,103.94;328.89,104.27;331.43,105.37;334.63,105.37;337.72,105.15;340.48,105.04;343.35,104.82;346.00,105.15;348.54,104.60;350.86,102.94;352.52,106.70;354.95,106.70;356.27,103.72;363.45,103.72;366.10,99.19;368.31,99.30;369.97,99.74;372.62,100.85;376.26,101.40;378.25,100.85;379.68,101.18;380.35,102.61;381.67,101.51;383.99,100.85;387.30,100.51;389.62,99.63;391.28,98.64;393.82,97.42;396.58,97.64;398.02,98.31;397.46,99.85;396.91,100.29;401.00,99.08;406.74,96.43;410.16,95.77;415.68,95.66;417.89,95.54;418.56,97.20;418.56,100.29;421.43,99.96;423.86,97.75;425.29,96.76;426.84,95.88;428.38,95.43;431.70,97.31;433.91,100.96;436.56,98.97;439.65,98.97;441.64,101.07;444.51,102.28;448.70,99.19;451.24,96.65;453.89,95.66;458.64,97.20;461.07,98.53;467.70,101.07;468.69,103.16;468.14,108.69;468.58,111.56;470.02,115.20;470.13,117.52;474.21,119.51;477.08,120.72;478.74,122.16;481.83,122.38;483.60,122.60;484.81,120.17;485.26,117.08;486.58,114.10;488.57,112.00;490.34,110.23;491.33,112.33;491.33,114.54;491.33,117.08;491.66,119.18;491.88,121.39;495.86,121.94;499.50,121.50;502.04,121.61;503.59,118.51;503.48,116.31;503.92,111.12;504.69,108.58;504.14,105.81;503.26,103.83;502.59,101.18;502.70,100.51;494.31,101.18;492.21,103.16;489.23,103.61;487.02,103.16;487.02,99.74;486.69,96.54;487.69,94.44;491.00,94.55;492.77,95.88;492.66,97.97;492.32,100.51;494.20,101.18;503.04,100.62;504.25,97.42;506.90,95.88;509.77,95.99;513.97,97.64;515.40,99.63;517.72,100.29;518.28,100.29;519.38,96.54;521.70,96.10;522.58,99.74;528.77,98.64;536.17,94.00;542.46,94.66;546.88,96.32;546.32,98.20;551.29,96.54;554.28,95.10;557.59,94.00;559.58,96.43;562.34,95.54;564.88,95.77;566.20,97.75;566.64,98.75;568.41,96.87;568.63,95.77;571.06,96.32;574.60,96.76;580.56,95.88;584.98,94.99;589.95,95.88;594.47,94.00;601.98,95.10;609.05,95.21;612.80,94.66;616.34,95.10;619.43,95.10;622.41,94.55;626.06,94.66;630.47,95.43;634.67,96.10;637.54,95.10;640.00,96.21;640.00,169.42;0.00,178.70" source="manual" z_order="0">
    </polygon>
    <polygon label="lake" occluded="0" points="0.00,125.31;6.08,125.10;9.40,125.93;12.71,125.93;16.03,126.35;19.14,126.76;22.25,126.97;25.78,127.18;30.96,127.59;34.49,127.80;38.22,127.80;42.37,127.80;45.68,127.80;48.79,128.01;52.11,127.80;55.64,127.80;59.16,128.01;62.69,128.01;66.63,128.63;70.57,128.42;74.92,128.21;78.24,128.21;82.39,128.84;86.33,128.84;89.64,128.84;93.58,129.04;96.90,128.84;100.01,129.25;103.54,129.04;106.86,128.84;109.97,129.25;113.49,129.25;120.13,129.46;123.86,129.87;127.18,130.08;127.38,130.08;140.45,130.49;146.46,131.95;146.25,132.15;154.13,130.49;157.87,129.87;160.56,128.01;160.77,125.93;165.95,125.52;170.72,124.27;174.46,124.27;177.57,124.48;177.77,127.80;180.88,129.46;183.58,131.53;187.73,132.36;191.04,131.95;194.15,131.53;197.47,131.32;200.79,131.32;205.77,132.15;209.08,132.36;213.85,132.15;217.17,131.95;220.49,132.78;223.81,132.57;227.12,132.36;230.65,131.95;233.97,131.53;237.08,130.70;241.22,129.04;244.34,128.84;247.45,128.63;249.93,126.14;257.81,127.18;261.96,126.97;266.11,127.18;271.08,126.97;275.02,126.55;278.76,126.35;282.70,125.93;286.01,126.35;284.98,128.21;292.24,128.84;297.00,129.67;300.74,129.46;304.68,129.04;309.86,129.04;315.05,129.25;317.33,129.25;317.33,132.78;322.51,135.68;329.15,137.75;334.12,137.96;338.27,137.75;341.59,137.96;370.82,140.45;413.96,141.90;438.22,142.11;445.06,143.35;456.05,142.73;467.45,142.52;475.13,144.39;478.24,144.18;481.97,143.97;484.87,143.77;489.85,143.77;495.66,143.56;498.77,143.97;504.99,145.22;510.79,145.01;515.98,144.39;520.75,143.77;524.06,143.77;526.76,144.18;529.87,144.39;536.09,144.60;539.62,144.39;540.24,144.39;553.92,144.80;572.38,144.39;572.59,137.54;573.42,132.78;574.04,127.38;572.38,126.14;572.59,123.65;587.72,123.03;615.72,122.82;636.04,121.99;640.00,122.41;640.00,640.00;0.00,640.00" source="manual" z_order="0">
    </polygon>
    <polygon label="pier" occluded="0" points="52.70,497.50;26.28,475.01;26.83,470.61;98.00,447.25;125.75,437.64;218.91,406.86;182.91,387.63;102.95,410.98;82.89,398.89;66.40,389.27;64.20,391.20;60.63,390.92;56.51,391.75;55.68,390.10;64.20,386.25;48.26,376.08;48.54,373.61;64.20,366.74;168.34,352.45;177.14,355.75;182.08,354.38;184.01,358.77;197.75,365.92;202.69,365.64;203.79,368.67;216.43,374.16;223.03,375.54;224.68,376.91;226.87,372.79;229.62,374.16;228.80,377.73;261.50,393.67;295.85,409.88;361.52,439.01;365.64,438.46;373.89,446.43;374.44,463.19;360.42,475.56;324.42,479.68;298.59,475.83;286.50,467.04;284.58,462.92;284.03,458.80;282.66,455.50;229.62,439.56;212.59,439.56;185.93,450.28;119.98,473.08;67.22,492.05" source="manual" z_order="2">
    </polygon>
    <polygon label="building" occluded="0" points="107.34,399.44;64.75,373.06;62.28,349.16;52.11,343.38;54.86,337.89;89.21,290.08;111.19,301.62;123.28,306.56;124.93,304.37;124.65,301.62;127.13,301.62;127.13,306.01;125.75,307.66;131.52,309.31;144.44,315.08;171.09,336.79;184.83,348.61;184.56,351.90;179.61,350.25;178.24,349.98;176.04,349.16;177.69,379.66" source="manual" z_order="3">
    </polygon>
    <polygon label="lighthouse" occluded="0" points="292.99,445.66;303.21,452.59;313.10,456.21;330.25,457.53;347.40,455.22;359.93,450.61;365.20,445.00;365.20,440.39;360.59,400.82;356.30,342.78;363.22,339.81;363.88,341.13;366.19,341.13;366.52,331.57;366.52,316.73;362.89,311.45;362.24,313.43;351.35,310.14;350.03,309.81;350.69,292.66;348.72,289.36;331.90,280.79;329.92,279.14;329.26,276.50;330.91,271.23;327.28,268.26;326.95,239.24;325.30,240.23;325.63,267.93;322.67,271.23;322.67,275.18;323.98,275.84;323.33,278.15;314.09,285.07;302.55,291.67;302.55,297.28;304.86,299.91;304.53,307.83;303.87,308.16;303.87,310.14;295.30,313.10;292.00,314.75;291.67,313.10;289.03,314.09;287.38,337.50;288.37,342.12;291.01,342.45;291.34,341.13;298.26,344.43;296.95,383.67;293.98,433.79;293.32,440.06" source="manual" z_order="4">
    </polygon>
    <polygon label="building" occluded="0" points="224.16,125.28;234.48,125.16;236.52,127.92;236.52,130.80;224.52,131.28;221.88,130.68;221.88,129.00;221.04,128.28" source="manual" z_order="4">
    </polygon>
    <polygon label="building" occluded="0" points="190.43,126.96;202.31,126.83;202.31,129.71;194.99,130.55;190.31,130.55" source="manual" z_order="4">
    </polygon>
    <polygon label="building" occluded="0" points="164.15,119.04;171.47,118.92;173.87,121.43;173.03,122.39;164.27,122.39" source="manual" z_order="4">
    </polygon>
    <polygon label="building" occluded="0" points="292.90,128.80;292.60,125.10;295.40,124.90;298.80,121.70;304.90,125.20;307.00,125.90;306.40,129.10;298.40,129.70;296.10,129.60" source="manual" z_order="5">
    </polygon>
    <polygon label="building" occluded="0" points="257.20,126.40;257.50,123.40;261.90,121.30;267.50,123.20;270.30,122.30;276.30,122.60;279.10,121.70;281.10,122.30;285.90,122.50;289.60,124.30;288.20,125.20;286.60,125.50;285.10,125.40;283.60,125.10;283.50,125.00;275.80,124.80;273.80,124.60;272.00,124.70;270.20,125.00;269.70,125.20;269.00,127.20;263.60,127.30;257.70,127.20" source="manual" z_order="5">
    </polygon>
    <polygon label="building" occluded="0" points="317.60,128.90;318.70,128.60;319.70,126.80;320.30,125.40;321.40,127.10;323.00,127.30;324.50,126.90;326.00,126.60;326.70,125.10;327.40,123.70;328.70,122.80;329.40,121.30;329.20,119.70;329.30,118.00;330.30,116.70;330.70,115.10;330.70,114.50;331.10,105.20;335.90,104.60;336.20,102.50;339.60,102.20;339.60,115.80;341.40,124.70;343.20,129.60;343.50,131.50;343.00,133.60;341.00,133.90;340.80,131.30;341.20,129.00;340.80,127.10;339.90,124.40;339.20,122.80;337.10,121.30;336.30,124.00;336.20,127.10;335.40,129.20;335.10,131.30;334.60,133.20;332.10,133.60;330.30,133.30;326.70,133.90;325.20,135.10;323.40,135.40;323.30,135.40;317.30,133.20" source="manual" z_order="6">
    </polygon>
    <polygon label="building" occluded="0" points="351.84,104.28;351.60,97.56;354.36,96.00;356.76,97.92;356.40,103.92;355.08,106.80;352.56,107.04" source="manual" z_order="7">
    </polygon>
    <polygon label="building" occluded="0" points="526.05,143.35;527.05,128.67;532.77,114.49;535.76,117.97;540.49,103.54;543.97,108.76;547.70,109.26;548.20,112.99;548.45,113.49;552.93,114.98;554.17,118.97;555.42,123.20;556.91,126.68;559.90,129.17;561.89,129.91;564.37,128.42;560.64,124.44;559.40,120.71;560.39,116.73;562.88,113.49;564.37,112.00;571.09,116.23;572.59,124.44;574.08,128.17;572.09,145.09;540.98,144.60;529.29,145.09" source="manual" z_order="8">
    </polygon>
    <polygon label="building" occluded="0" points="602.52,118.80;599.64,118.68;597.84,118.32;596.88,116.76;597.48,114.84;599.76,114.72;601.92,113.88;603.48,112.32;605.04,111.36;606.84,111.60;609.48,112.08;611.28,112.56;612.48,114.00;614.40,114.36;616.20,113.64;617.76,112.68;619.56,112.44;621.12,111.48;623.52,110.76;625.80,110.52;627.60,110.16;629.52,110.04;631.56,110.88;633.84,111.72;635.52,113.16;636.60,114.84;636.84,115.44;636.48,117.36;635.64,122.40;613.32,123.00;615.36,121.20;615.48,119.16;612.48,119.40;611.04,119.64;605.76,119.76;603.96,119.28;603.84,119.28" source="manual" z_order="9">
    </polygon>
  </image>
</annotations>